{
  "hash": "7353044c",
  "configHash": "6ccdeb8e",
  "lockfileHash": "2bbe39ad",
  "browserHash": "74d08d97",
  "optimized": {
    "vue": {
      "src": "../../../../node_modules/.pnpm/vue@3.4.21_typescript@5.4.3/node_modules/vue/dist/vue.runtime.esm-bundler.js",
      "file": "vue.js",
      "fileHash": "a88e21aa",
      "needsInterop": false
    },
    "vitepress > @vue/devtools-api": {
      "src": "../../../../node_modules/.pnpm/@vue+devtools-api@7.0.24_vue@3.4.21/node_modules/@vue/devtools-api/dist/index.js",
      "file": "vitepress___@vue_devtools-api.js",
      "fileHash": "dd53d62f",
      "needsInterop": false
    },
    "vitepress > @vueuse/core": {
      "src": "../../../../node_modules/.pnpm/@vueuse+core@10.9.0_vue@3.4.21/node_modules/@vueuse/core/index.mjs",
      "file": "vitepress___@vueuse_core.js",
      "fileHash": "500d9b2e",
      "needsInterop": false
    },
    "@theme/index": {
      "src": "../../../../node_modules/.pnpm/vitepress@1.0.1_@algolia+client-search@4.23.1_@types+node@20.11.30_postcss@8.4.38_search-insi_zxzycvbct3ljr6guld6flpaxje/node_modules/vitepress/dist/client/theme-default/index.js",
      "file": "@theme_index.js",
      "fileHash": "c3036d48",
      "needsInterop": false
    }
  },
  "chunks": {
    "chunk-P7UHUIOU": {
      "file": "chunk-P7UHUIOU.js"
    },
    "chunk-CUUO7HFL": {
      "file": "chunk-CUUO7HFL.js"
    }
  }
}